pygleton/__init__.py
pygleton/py.typed
pygleton-1.0.1.dist-info/LICENSE
pygleton-1.0.1.dist-info/METADATA
pygleton-1.0.1.dist-info/WHEEL
pygleton-1.0.1.dist-info/RECORD
