Metadata-Version: 2.1
Name: pygleton
Version: 1.0.1
Summary: Decorator for implementing singleton classes
Home-page: https://github.com/pragmatic-fi/pygleton
Keywords: decorator,singleton
Author: The Pragmatic Solutions
Author-email: contact@thepragmatic.fi
Requires-Python: >=3.11,<4.0
Classifier: Development Status :: 4 - Beta
Classifier: Intended Audience :: Developers
Classifier: License :: OSI Approved :: BSD License
Classifier: Programming Language :: Python :: 3
Classifier: Programming Language :: Python :: 3.11
Classifier: Programming Language :: Python :: 3.12
Project-URL: Repository, https://github.com/pragmatic-fi/pygleton.git
